LICENSE
README.md
setup.cfg
setup.py
aws_adfs_auth/__init__.py
aws_adfs_auth/abstract_adfs.py
aws_adfs_auth/cli.py
aws_adfs_auth/configuration.py
aws_adfs_auth/main.py
aws_adfs_auth/ms_adfs.py
aws_adfs_auth/utils.py
aws_adfs_auth.egg-info/PKG-INFO
aws_adfs_auth.egg-info/SOURCES.txt
aws_adfs_auth.egg-info/dependency_links.txt
aws_adfs_auth.egg-info/entry_points.txt
aws_adfs_auth.egg-info/requires.txt
aws_adfs_auth.egg-info/top_level.txt