Metadata-Version: 1.1
Name: aws-adfs-auth
Version: 0.4.0
Summary: aws_adfs_auth command line utility
Home-page: https://github.com/jschwellach/aws-adfs-auth
Author: Janos Schwellach
Author-email: jschwellach@gmail.com
License: APACHE2
Platform: UNKNOWN
Classifier: Development Status :: 4 - Beta
Classifier: Environment :: Console
Classifier: Intended Audience :: End Users/Desktop
Classifier: Intended Audience :: Information Technology
Classifier: License :: OSI Approved :: Apache Software License
Classifier: Operating System :: POSIX
Classifier: Operating System :: Microsoft :: Windows
Classifier: Operating System :: MacOS :: MacOS X
Classifier: Topic :: Utilities
Classifier: Programming Language :: Python
Classifier: Programming Language :: Python :: 3.6
Classifier: Programming Language :: Python :: 3.7
